CHANGES.txt
LICENSE.txt
MANIFEST.in
README.txt
setup.cfg
setup.py
version.txt
raisin.pyramid.egg-info/PKG-INFO
raisin.pyramid.egg-info/SOURCES.txt
raisin.pyramid.egg-info/dependency_links.txt
raisin.pyramid.egg-info/entry_points.txt
raisin.pyramid.egg-info/not-zip-safe
raisin.pyramid.egg-info/requires.txt
raisin.pyramid.egg-info/top_level.txt
raisinpyramid/__init__.py
raisinpyramid/login.py
raisinpyramid/security.py
raisinpyramid/views.py
raisinpyramid/static/favicon.ico
raisinpyramid/static/footerbg.png
raisinpyramid/static/headerbg.png
raisinpyramid/static/ie6.css
raisinpyramid/static/middlebg.png
raisinpyramid/static/pylons.css
raisinpyramid/static/pyramid-small.png
raisinpyramid/static/pyramid.png
raisinpyramid/static/transparent.gif
raisinpyramid/templates/login.pt